aspmc/__init__.py
aspmc/config.py
aspmc/main.py
aspmc/signal_handling.py
aspmc/stats.py
aspmc/util.py
aspmc/compile/__init__.py
aspmc/compile/circuit.py
aspmc/compile/cnf.py
aspmc/compile/constrained_compile.py
aspmc/compile/constrained_ddnnf.py
aspmc/compile/constrained_sdd.py
aspmc/compile/dtree.py
aspmc/compile/vtree.py
aspmc/external/UWrMaxSAT/uwrmaxsat/LICENSE
aspmc/external/UWrMaxSAT/uwrmaxsat/build/release/bin/uwrmaxsat
aspmc/external/d4/.git
aspmc/external/d4/.gitignore
aspmc/external/d4/LICENSE
aspmc/external/d4/Makefile
aspmc/external/d4/README.md
aspmc/external/d4/d4_static
aspmc/external/d4/DAG/BinaryDeterministicOrNode.hh
aspmc/external/d4/DAG/BinaryDeterministicOrNodeCertified.hh
aspmc/external/d4/DAG/Branch.hh
aspmc/external/d4/DAG/ConstantNode.hh
aspmc/external/d4/DAG/DAG.hh
aspmc/external/d4/DAG/DecomposableAndNode.hh
aspmc/external/d4/DAG/DecomposableAndNodeCerified.hh
aspmc/external/d4/DAG/DeterministicOrNode.hh
aspmc/external/d4/DAG/False.hh
aspmc/external/d4/DAG/ImplicitAnd.hh
aspmc/external/d4/DAG/KromFormula.hh
aspmc/external/d4/DAG/PCNode.hh
aspmc/external/d4/DAG/RenamableHornFormula.hh
aspmc/external/d4/DAG/Root.hh
aspmc/external/d4/DAG/True.hh
aspmc/external/d4/DAG/UnaryNode.hh
aspmc/external/d4/DAG/UnaryNodeCertified.hh
aspmc/external/d4/benchTest/bug.cnf
aspmc/external/d4/benchTest/littleTest.cnf
aspmc/external/d4/benchTest/littleTest.w
aspmc/external/d4/benchTest/one.cnf
aspmc/external/d4/benchTest/projected.var
aspmc/external/d4/benchTest/test1.cnf
aspmc/external/d4/compilers/dDnnfCompiler.hh
aspmc/external/d4/core/Main.cc
aspmc/external/d4/core/Main.hh
aspmc/external/d4/core/ShareStructures.hh
aspmc/external/d4/hashing/HashCnf.hh
aspmc/external/d4/heuristics/ClauseBipartiteGraphPartitioner.cc
aspmc/external/d4/heuristics/ClauseBipartiteGraphPartitioner.hh
aspmc/external/d4/heuristics/MinCutPartitioner.cc
aspmc/external/d4/heuristics/MinCutPartitioner.hh
aspmc/external/d4/heuristics/PhaseHeuristic.hh
aspmc-1.1.1.dist-info/LICENSE
aspmc-1.1.1.dist-info/METADATA
aspmc-1.1.1.dist-info/WHEEL
aspmc-1.1.1.dist-info/entry_points.txt
aspmc-1.1.1.dist-info/top_level.txt
aspmc-1.1.1.dist-info/RECORD
