Metadata-Version: 2.1
Name: aspmc
Version: 1.1.1
Summary: An efficient algebraic model counter.
Home-page: https://github.com/raki123/aspmc
Author: R. Kiesel
Author-email: rafael.kiesel@tuwien.ac.at
License: MIT
Keywords: probabilistic,model counting,logic programming,answer set programming
Classifier: Development Status :: 4 - Beta
Classifier: Topic :: Scientific/Engineering
Classifier: Topic :: Scientific/Engineering :: Artificial Intelligence
Classifier: License :: OSI Approved :: MIT License
Classifier: Programming Language :: Python :: 3
Classifier: Programming Language :: Python :: 3.6
Classifier: Programming Language :: Python :: 3.7
Classifier: Programming Language :: Python :: 3.8
Classifier: Programming Language :: Python :: 3.9
Classifier: Programming Language :: Python :: 3.10
Classifier: Programming Language :: Python :: 3 :: Only
Requires-Python: >=3.6, <4
License-File: LICENSE
Requires-Dist: psutil
Requires-Dist: networkx
Requires-Dist: numpy
Requires-Dist: lark
Requires-Dist: clingo
Requires-Dist: matplotlib
Requires-Dist: dataclasses
Requires-Dist: sympy
